{
    "Monday": {
      "Breakfast": ["Idli", "Milk", "Tea", "Bread, Butter, Jam", "Banana"],
      "Lunch": ["Chapati", "Lobia", "Rice", "Dal Tadka", "Salad, Achar, Papad", "Chach"],
      "Snacks": ["Coffee", "Upma"],
      "Dinner": ["Chapati", "Matar Aloo", "Jeera Rice", "Dal Makhani", "Salad, Achar"]
    },
    "Tuesday": {
      "Breakfast": ["Uttapam", "Milk", "Tea", "Bread, Butter, Jam", "Seasonal Fruit"],
      "Lunch": ["Chapati", "Soya Wadi", "Mutter Rice", "Dal", "Salad, Achar", "Curd"],
      "Snacks": ["Tea", "White Sauce Pasta"],
      "Dinner": ["Chapati", "Gatta Curry", "Rice", "Sambhar", "Salad, Achar", "Jalebi"]
    },
    "Wednesday": {
      "Breakfast": ["Aloo Paratha", "Milk", "Tea", "Bread, Butter, Jam", "Banana", "Curd"],
      "Lunch": ["Chapati", "Sem Aloo", "Pulav Rice", "Kadi Pakoda", "Salad, Achar, Papad"],
      "Snacks": ["Tea", "Sev Poha"],
      "Dinner": ["Chapati", "Paneer", "Rice", "Dal", "Salad, Achar"]
    },
    "Thursday": {
      "Breakfast": ["Aloo Puri", "Milk", "Tea", "Bread, Butter, Jam", "Seasonal Fruit"],
      "Lunch": ["Chapati", "Desi Chana Gravy", "Rice", "Masur Dal", "Salad, Achar", "Curd"],
      "Snacks": ["Tea", "Fried Rice"],
      "Dinner": ["Chapati", "Corn Palak", "Tomato Rice", "Chana Dal", "Salad, Achar", "Gulab Jamun"]
    },
    "Friday": {
      "Breakfast": ["Wada", "Milk", "Tea", "Bread, Butter, Jam", "Seasonal Fruit"],
      "Lunch": ["Paratha", "Sev Bhaji", "Mutter Rice", "Moong Dal", "Salad, Achar", "Chach"],
      "Snacks": ["Tea", "Chana Masala"],
      "Dinner": ["Chapati", "Mix Veg", "Rice", "Sambhar", "Achar"]
    },
    "Saturday": {
      "Breakfast": ["Dosa", "Milk", "Tea", "Bread, Butter, Jam", "Banana"],
      "Lunch": ["Chapati", "Rajma Curry", "Lemon Rice", "Dal Fry", "Salad, Achar", "Lassi"],
      "Snacks": ["Tea", "Samosa/Bread Pakoda", "Green Chutney"],
      "Dinner": ["Chapati", "Methi Matar", "Rice", "Chana Dal", "Salad, Achar"]
    },
    "Sunday": {
      "Breakfast": ["Poha", "Milk", "Tea", "Bread, Butter, Jam", "Seasonal Fruit"],
      "Lunch": ["Puri", "Chole", "Rice", "Moong Dal", "Salad, Achar", "Boondi Raita"],
      "Snacks": ["Tea", "Cup Cakes/Dhokla"],
      "Dinner": ["Chapati", "Kadhai Paneer", "Jeera Rice", "Dal Fry", "Salad, Achar", "Ice Cream/Rasgulla"]
    }
  }